hossam/NotoSansKR-Regular.ttf
hossam/__init__.py
hossam/data_loader.py
hossam/hs_classroom.py
hossam/hs_gis.py
hossam/hs_plot.py
hossam/hs_prep.py
hossam/hs_stats.py
hossam/hs_timeserise.py
hossam/hs_util.py
hossam/leekh.png
hossam/mcp/__init__.py
hossam/mcp/hs_classroom.py
hossam/mcp/hs_gis.py
hossam/mcp/hs_plot.py
hossam/mcp/hs_prep.py
hossam/mcp/hs_stats.py
hossam/mcp/hs_timeserise.py
hossam/mcp/hs_util.py
hossam/mcp/loader.py
hossam/mcp/server.py
hossam-0.3.20.dist-info/licenses/LICENSE
hossam-0.3.20.dist-info/METADATA
hossam-0.3.20.dist-info/WHEEL
hossam-0.3.20.dist-info/entry_points.txt
hossam-0.3.20.dist-info/top_level.txt
hossam-0.3.20.dist-info/RECORD
