Metadata-Version: 2.4
Name: hossam
Version: 0.3.20
Summary: Hossam Data Helper
Author-email: Lee Kwang-Ho <leekh4232@gmail.com>
License-Expression: MIT
Project-URL: Homepage, https://github.com/leekh4232/hossam-py
Project-URL: Repository, https://github.com/leekh4232/hossam-py
Keywords: data,analysis,helper,hossam,tensorflow
Classifier: Development Status :: 3 - Alpha
Classifier: Intended Audience :: Developers
Classifier: Topic :: Software Development :: Libraries
Classifier: Programming Language :: Python :: 3
Classifier: Programming Language :: Python :: 3 :: Only
Requires-Python: >=3.11
License-File: LICENSE
Requires-Dist: tqdm
Requires-Dist: tabulate
Requires-Dist: pandas
Requires-Dist: matplotlib
Requires-Dist: seaborn
Requires-Dist: requests
Requires-Dist: openpyxl
Requires-Dist: xlrd
Requires-Dist: statsmodels
Requires-Dist: scipy
Requires-Dist: scikit-learn
Requires-Dist: pingouin
Requires-Dist: statannotations
Requires-Dist: joblib
Requires-Dist: geopandas
Requires-Dist: kmodes
Requires-Dist: pmdarima
Requires-Dist: prophet
Requires-Dist: plotly
Requires-Dist: jenkspy
Dynamic: license-file
